{
  "utter_citizenship_by_descent_documents": {
    "precision": 1.0,
    "recall": 1.0,
    "f1-score": 1.0,
    "support": 2
  },
  "utter_citizenship_by_birth_eligibility_romanized": {
    "precision": 1.0,
    "recall": 1.0,
    "f1-score": 1.0,
    "support": 2
  },
  "utter_citizenship": {
    "precision": 1.0,
    "recall": 1.0,
    "f1-score": 1.0,
    "support": 1
  },
  "utter_marriage_certificate_documents_romanized": {
    "precision": 1.0,
    "recall": 1.0,
    "f1-score": 1.0,
    "support": 2
  },
  "utter_birth_certificate_documents": {
    "precision": 1.0,
    "recall": 1.0,
    "f1-score": 1.0,
    "support": 2
  },
  "utter_citizenship_by_naturalization_option1": {
    "precision": 0.5,
    "recall": 1.0,
    "f1-score": 0.6666666666666666,
    "support": 1
  },
  "utter_migration_certificate_steps": {
    "precision": 1.0,
    "recall": 1.0,
    "f1-score": 1.0,
    "support": 2
  },
  "utter_citizenship_romanized": {
    "precision": 1.0,
    "recall": 1.0,
    "f1-score": 1.0,
    "support": 1
  },
  "utter_citizenship_by_birth_documents_romanized": {
    "precision": 1.0,
    "recall": 1.0,
    "f1-score": 1.0,
    "support": 2
  },
  "utter_citizenship_by_birth_steps_romanized": {
    "precision": 1.0,
    "recall": 1.0,
    "f1-score": 1.0,
    "support": 2
  },
  "utter_citizenship_by_naturalization": {
    "precision": 1.0,
    "recall": 1.0,
    "f1-score": 1.0,
    "support": 2
  },
  "utter_divorce_certificate_documents_romanized": {
    "precision": 1.0,
    "recall": 1.0,
    "f1-score": 1.0,
    "support": 2
  },
  "action_listen": {
    "precision": 0.9814814814814815,
    "recall": 0.9814814814814815,
    "f1-score": 0.9814814814814815,
    "support": 54
  },
  "utter_marriage_certificate_documents": {
    "precision": 1.0,
    "recall": 1.0,
    "f1-score": 1.0,
    "support": 2
  },
  "utter_marriage_certificate_steps_romanized": {
    "precision": 1.0,
    "recall": 0.5,
    "f1-score": 0.6666666666666666,
    "support": 2
  },
  "utter_divorce_certificate_documents": {
    "precision": 1.0,
    "recall": 1.0,
    "f1-score": 1.0,
    "support": 2
  },
  "utter_citizenship_by_descent_documents_romanized": {
    "precision": 1.0,
    "recall": 1.0,
    "f1-score": 1.0,
    "support": 2
  },
  "utter_marriage_certificate_steps": {
    "precision": 0.6666666666666666,
    "recall": 1.0,
    "f1-score": 0.8,
    "support": 2
  },
  "utter_citizenship_by_descent_steps_romanized": {
    "precision": 1.0,
    "recall": 1.0,
    "f1-score": 1.0,
    "support": 2
  },
  "utter_citizenship_by_naturalization_option2": {
    "precision": 0.0,
    "recall": 0.0,
    "f1-score": 0.0,
    "support": 1
  },
  "utter_migration_certificate_documents": {
    "precision": 1.0,
    "recall": 1.0,
    "f1-score": 1.0,
    "support": 2
  },
  "utter_death_certificate_documents": {
    "precision": 0.6666666666666666,
    "recall": 1.0,
    "f1-score": 0.8,
    "support": 2
  },
  "utter_citizenship_by_descent_eligibility_romanized": {
    "precision": 1.0,
    "recall": 1.0,
    "f1-score": 1.0,
    "support": 2
  },
  "utter_death_certificate_documents_romanized": {
    "precision": 1.0,
    "recall": 0.5,
    "f1-score": 0.6666666666666666,
    "support": 2
  },
  "utter_migration_certificate_documents_romanized": {
    "precision": 1.0,
    "recall": 1.0,
    "f1-score": 1.0,
    "support": 2
  },
  "utter_citizenship_by_descent_eligibility": {
    "precision": 1.0,
    "recall": 1.0,
    "f1-score": 1.0,
    "support": 2
  },
  "action_handle_citizenship_query_romanized": {
    "precision": 1.0,
    "recall": 1.0,
    "f1-score": 1.0,
    "support": 1
  },
  "utter_divorce_certificate_steps": {
    "precision": 1.0,
    "recall": 1.0,
    "f1-score": 1.0,
    "support": 2
  },
  "utter_citizenship_by_birth_documents": {
    "precision": 1.0,
    "recall": 1.0,
    "f1-score": 1.0,
    "support": 2
  },
  "utter_citizenship_by_birth_steps": {
    "precision": 1.0,
    "recall": 1.0,
    "f1-score": 1.0,
    "support": 2
  },
  "utter_divorce_certificate_steps_romanized": {
    "precision": 1.0,
    "recall": 1.0,
    "f1-score": 1.0,
    "support": 2
  },
  "utter_birth_certificate_documents_romanized": {
    "precision": 1.0,
    "recall": 1.0,
    "f1-score": 1.0,
    "support": 2
  },
  "utter_death_certificate_steps_romanized": {
    "precision": 1.0,
    "recall": 1.0,
    "f1-score": 1.0,
    "support": 2
  },
  "utter_death_certificate_steps": {
    "precision": 1.0,
    "recall": 1.0,
    "f1-score": 1.0,
    "support": 2
  },
  "utter_birth_certificate_steps_romanized": {
    "precision": 1.0,
    "recall": 1.0,
    "f1-score": 1.0,
    "support": 2
  },
  "utter_birth_certificate_steps": {
    "precision": 1.0,
    "recall": 1.0,
    "f1-score": 1.0,
    "support": 2
  },
  "utter_citizenship_by_birth_eligibility": {
    "precision": 1.0,
    "recall": 1.0,
    "f1-score": 1.0,
    "support": 2
  },
  "utter_migration_certificate_steps_romanized": {
    "precision": 1.0,
    "recall": 1.0,
    "f1-score": 1.0,
    "support": 2
  },
  "action_handle_citizenship_query": {
    "precision": 1.0,
    "recall": 1.0,
    "f1-score": 1.0,
    "support": 1
  },
  "utter_citizenship_by_descent_steps": {
    "precision": 1.0,
    "recall": 1.0,
    "f1-score": 1.0,
    "support": 2
  },
  "accuracy": 0.9682539682539683,
  "macro avg": {
    "precision": 0.9453703703703702,
    "recall": 0.9495370370370371,
    "f1-score": 0.9395370370370368,
    "support": 126
  },
  "weighted avg": {
    "precision": 0.9695767195767195,
    "recall": 0.9682539682539683,
    "f1-score": 0.9645502645502645,
    "support": 126
  },
  "micro avg": {
    "precision": 0.9682539682539683,
    "recall": 0.9682539682539683,
    "f1-score": 0.9682539682539683,
    "support": 126
  },
  "conversation_accuracy": {
    "accuracy": 0.92,
    "correct": 46,
    "with_warnings": 0,
    "total": 50
  }
}